{"gtabs":[{"panes":[{"ptabs":[{"history":[{"dir":"/home/cliffordc/.librewolf/w50izy8g.default-release/startscreen/icons","file":"discord.svg","relpos":2,"ts":1635768155},{"dir":"/home/cliffordc/.librewolf/w50izy8g.default-release/startscreen","file":"icons","relpos":2,"ts":1635768155},{"dir":"/home/cliffordc/.librewolf/w50izy8g.default-release/startscreen/icons","file":"github.svg","relpos":2,"ts":1635768155},{"dir":"/home/cliffordc","file":".librewolf","relpos":12,"ts":1635768155},{"dir":"/home","file":"cliffordc","relpos":1,"ts":1635768155},{"dir":"/home/cliffordc","file":"Downloads","relpos":24,"ts":1635768155},{"dir":"/home/cliffordc/Downloads","file":"We10X-special.tar.xz","relpos":4,"ts":1635768155},{"dir":"/home/cliffordc","file":".librewolf","relpos":4,"ts":1635768155},{"dir":"/home/cliffordc/.librewolf","file":"w50izy8g.default-release","relpos":2,"ts":1635768155},{"dir":"/home/cliffordc/.librewolf/w50izy8g.default-release","file":"startscreen","relpos":8,"ts":1635768155},{"dir":"/home/cliffordc/.librewolf/w50izy8g.default-release/startscreen","file":"icons","relpos":2,"ts":1635768155},{"dir":"/home/cliffordc/.librewolf/w50izy8g.default-release/startscreen/icons","file":"discord.svg","relpos":2,"ts":1635768155},{"dir":"/home/cliffordc/.librewolf/w50izy8g.default-release/startscreen","file":"icons","relpos":2,"ts":1635768155},{"dir":"/home/cliffordc/.librewolf/w50izy8g.default-release/startscreen/icons","file":"github.svg","relpos":2,"ts":1635768155},{"dir":"/home/cliffordc","file":"Downloads","relpos":24,"ts":1635768201},{"dir":"/home/cliffordc/Downloads","file":"We10X-special.tar.xz","relpos":4,"ts":1635768201},{"dir":"/home/cliffordc","file":".librewolf","relpos":4,"ts":1635768201},{"dir":"/home/cliffordc/.librewolf","file":"w50izy8g.default-release","relpos":2,"ts":1635768201},{"dir":"/home/cliffordc/.librewolf/w50izy8g.default-release","file":"startscreen","relpos":8,"ts":1635768201},{"dir":"/home/cliffordc/.librewolf/w50izy8g.default-release/startscreen","file":"icons","relpos":2,"ts":1635768201},{"dir":"/home/cliffordc/.librewolf/w50izy8g.default-release/startscreen/icons","file":"discord.svg","relpos":2,"ts":1635768201},{"dir":"/home/cliffordc/.librewolf/w50izy8g.default-release/startscreen","file":"startscreen.css","relpos":3,"ts":1635768201},{"dir":"/home/cliffordc","file":"Downloads","relpos":24,"ts":1635768201},{"dir":"/home/cliffordc/Downloads","file":"We10X-special.tar.xz","relpos":4,"ts":1635768201},{"dir":"/home/cliffordc","file":".librewolf","relpos":4,"ts":1635768201},{"dir":"/home/cliffordc/.librewolf","file":"w50izy8g.default-release","relpos":2,"ts":1635768201},{"dir":"/home/cliffordc/.librewolf/w50izy8g.default-release","file":"startscreen","relpos":8,"ts":1635768201},{"dir":"/home/cliffordc/.librewolf/w50izy8g.default-release/startscreen","file":"icons","relpos":2,"ts":1635768201},{"dir":"/home/cliffordc/.librewolf/w50izy8g.default-release/startscreen/icons","file":"discord.svg","relpos":2,"ts":1635768201},{"dir":"/home/cliffordc/.librewolf/w50izy8g.default-release/startscreen","file":"startscreen.css","relpos":3,"ts":1635768201},{"dir":"/home/cliffordc","file":"Downloads","relpos":24,"ts":1635768201},{"dir":"/home/cliffordc/Downloads","file":"We10X-special.tar.xz","relpos":4,"ts":1635768201},{"dir":"/home/cliffordc","file":".librewolf","relpos":4,"ts":1635768201},{"dir":"/home/cliffordc/.librewolf","file":"w50izy8g.default-release","relpos":2,"ts":1635768201},{"dir":"/home/cliffordc/.librewolf/w50izy8g.default-release","file":"startscreen","relpos":8,"ts":1635768201},{"dir":"/home/cliffordc/.librewolf/w50izy8g.default-release/startscreen","file":"icons","relpos":2,"ts":1635768201},{"dir":"/home/cliffordc/.librewolf/w50izy8g.default-release/startscreen/icons","file":"discord.svg","relpos":2,"ts":1635768201},{"dir":"/home/cliffordc/.librewolf/w50izy8g.default-release/startscreen","file":"startscreen.css","relpos":3,"ts":1635768201},{"dir":"/home/cliffordc","file":"Downloads","relpos":24,"ts":1635768201},{"dir":"/home/cliffordc/Downloads","file":"We10X-special.tar.xz","relpos":4,"ts":1635768201},{"dir":"/home/cliffordc","file":".librewolf","relpos":4,"ts":1635768201},{"dir":"/home/cliffordc/.librewolf","file":"w50izy8g.default-release","relpos":2,"ts":1635768201},{"dir":"/home/cliffordc/.librewolf/w50izy8g.default-release","file":"startscreen","relpos":8,"ts":1635768201},{"dir":"/home/cliffordc/.librewolf/w50izy8g.default-release/startscreen","file":"icons","relpos":2,"ts":1635768201},{"dir":"/home/cliffordc/.librewolf/w50izy8g.default-release/startscreen/icons","file":"discord.svg","relpos":2,"ts":1635768201},{"dir":"/home/cliffordc/.librewolf/w50izy8g.default-release/startscreen","file":"startscreen.css","relpos":3,"ts":1635768201},{"dir":"/home/cliffordc","file":".config","relpos":4,"ts":1635770246},{"dir":"/home/cliffordc/.config","file":"bspwm","relpos":4,"ts":1635770246},{"dir":"/home/cliffordc/.config/bspwm","file":"bspwmrc","relpos":1,"ts":1635770246},{"dir":"/home/cliffordc","file":".config","relpos":4,"ts":1635770246},{"dir":"/home/cliffordc/.config","file":"bspwm","relpos":4,"ts":1635770246},{"dir":"/home/cliffordc/.config/bspwm","file":"bspwmrc","relpos":1,"ts":1635770246},{"dir":"/home/cliffordc","file":"Pictures","relpos":37,"ts":1635914690},{"dir":"/home/cliffordc/Pictures","file":"Wallpapers","relpos":2,"ts":1635914690},{"dir":"/home/cliffordc/Pictures/Wallpapers","file":"6TpQM38.png","relpos":1,"ts":1635914690},{"dir":"/home/cliffordc/Pictures","file":"Wallpapers","relpos":2,"ts":1635914821},{"dir":"/home/cliffordc","file":"Downloads","relpos":34,"ts":1635914821},{"dir":"/home/cliffordc/Downloads","file":"We10X-special.tar.xz","relpos":5,"ts":1635914821},{"dir":"/home/cliffordc","file":"Pictures","relpos":37,"ts":1635914821},{"dir":"/home/cliffordc/Pictures","file":"Wallpapers","relpos":2,"ts":1635914821},{"dir":"/home/cliffordc/Pictures/Wallpapers","file":"dystopian-landscape-ft-9s-from-nierautomata--1920×1080.jpg","relpos":21,"ts":1635914821},{"dir":"/home/cliffordc","file":"Downloads","relpos":34,"ts":1635914821},{"dir":"/home/cliffordc/Downloads","file":"We10X-special.tar.xz","relpos":4,"ts":1635914821},{"dir":"/home/cliffordc","file":"Pictures","relpos":37,"ts":1635914821},{"dir":"/home/cliffordc/Pictures","file":"Wallpapers","relpos":2,"ts":1635914821},{"dir":"/home/cliffordc/Pictures/Wallpapers","file":"evangelion-4-1920×1080.jpg","relpos":24,"ts":1635914821},{"dir":"/home/cliffordc/.config/bspwm","file":"bspwmrc","relpos":1,"ts":1636702307},{"dir":"/home/cliffordc/.config","file":"bspwm","relpos":4,"ts":1637307525},{"dir":"/home/cliffordc","file":".config","relpos":4,"ts":1637307525},{"dir":"/home/cliffordc/.config","file":"bspwm","relpos":4,"ts":1637307525},{"dir":"/home/cliffordc/.config/bspwm","file":"bspwmrc","relpos":1,"ts":1637307525},{"dir":"/home/cliffordc/.config","file":"bspwm","relpos":4,"ts":1638513913},{"dir":"/home/cliffordc/.config/bspwm","file":"bspwmrc","relpos":1,"ts":1638513913},{"dir":"/home/cliffordc/.config","file":"sxhkd","relpos":40,"ts":1638513913},{"dir":"/home/cliffordc/.config/sxhkd","file":"..","relpos":0,"ts":1638513913},{"dir":"/home/cliffordc/.config","file":"sxhkd","relpos":40,"ts":1638513913},{"dir":"/home/cliffordc/.config/sxhkd","file":"sxhkdrc","relpos":1,"ts":1638513913},{"dir":"/home/cliffordc/.config","file":"bspwm","relpos":4,"ts":1638514895},{"dir":"/home/cliffordc/.config/bspwm","file":"bspwmrc","relpos":1,"ts":1638514895},{"dir":"/home/cliffordc/.config","file":"cmus","relpos":7,"ts":1638709760},{"dir":"/home/cliffordc","file":".config","relpos":4,"ts":1638709760},{"dir":"/home/cliffordc/.config","file":"nvim","relpos":33,"ts":1638709760},{"dir":"/home/cliffordc/.config/nvim","file":"lua","relpos":1,"ts":1638709760},{"dir":"/home/cliffordc/.config/nvim/lua","file":"telescope-config.lua","relpos":14,"ts":1638709760},{"dir":"/home/cliffordc/.config/nvim","file":"lua","relpos":1,"ts":1638709760},{"dir":"/home/cliffordc/.config/nvim/lua","file":"clifford","relpos":1,"ts":1638709760},{"dir":"/home/cliffordc/.config/nvim/lua/clifford","file":"telescope","relpos":1,"ts":1638709760},{"dir":"/home/cliffordc/.config/nvim/lua/clifford/telescope","file":"init.lua","relpos":1,"ts":1638709760},{"dir":"/home/cliffordc/.config/nvim/lua/clifford","file":"telescope","relpos":1,"ts":1638709760},{"dir":"/home/cliffordc/.config/nvim/lua","file":"clifford","relpos":1,"ts":1638709760},{"dir":"/home/cliffordc/.config/nvim","file":"lua","relpos":1,"ts":1638709760},{"dir":"/home/cliffordc/.config","file":"alacritty","relpos":4,"ts":1638709760},{"dir":"/home/cliffordc/.config/alacritty","file":"alacritty.yml","relpos":1,"ts":1638709760},{"dir":"/home/cliffordc/.config","file":"nvim","relpos":36,"ts":1638766095},{"dir":"/home/cliffordc/.config/nvim","file":"lua","relpos":1,"ts":1638766095},{"dir":"/home/cliffordc/.config/nvim/lua","file":"settings.lua","relpos":12,"ts":1638766095},{"dir":"/home/cliffordc/.config/nvim","file":"init.lua","relpos":2,"ts":1638766740},{"dir":"/home/cliffordc/.config","file":"nvim","relpos":36,"ts":1638766740},{"dir":"/home/cliffordc/.config/nvim","file":"lua","relpos":1,"ts":1638766740},{"dir":"/home/cliffordc/.config/nvim/lua","file":"plugins.lua","relpos":10,"ts":1638766740}],"filters":{"invert":true,"dot":false,"manual":"","auto":""},"last-location":"/home/cliffordc/.config/nvim/lua","sorting":[2],"preview":true}]},{"ptabs":[{"history":[{"dir":"/sys/class","file":"nvme-subsystem","relpos":8,"ts":1634392892},{"dir":"/etc/bluetooth","file":"main.conf","relpos":1,"ts":1634392892},{"dir":"/etc","file":"bluetooth","relpos":12,"ts":1634392892},{"dir":"/","file":"home","relpos":4,"ts":1634392892},{"dir":"/home","file":"cliffordc","relpos":1,"ts":1634392892},{"dir":"/","file":"sys","relpos":15,"ts":1634392892},{"dir":"/sys","file":"block","relpos":1,"ts":1634392892},{"dir":"/sys/block","file":"loop0","relpos":1,"ts":1634392892},{"dir":"/sys","file":"bus","relpos":2,"ts":1634392892},{"dir":"/sys/bus","file":"gpio","relpos":11,"ts":1634392892},{"dir":"/sys","file":"class","relpos":3,"ts":1634392892},{"dir":"/sys/class","file":"nvme-subsystem","relpos":13,"ts":1634392892},{"dir":"/etc/bluetooth","file":"main.conf","relpos":1,"ts":1634392892},{"dir":"/etc","file":"bluetooth","relpos":12,"ts":1634392892},{"dir":"/","file":"home","relpos":4,"ts":1634392892},{"dir":"/home","file":"cliffordc","relpos":1,"ts":1634392892},{"dir":"/","file":"sys","relpos":15,"ts":1634392892},{"dir":"/sys","file":"block","relpos":1,"ts":1634392892},{"dir":"/sys/block","file":"loop0","relpos":1,"ts":1634392892},{"dir":"/sys","file":"bus","relpos":2,"ts":1634392892},{"dir":"/sys/bus","file":"gpio","relpos":11,"ts":1634392892},{"dir":"/sys","file":"class","relpos":3,"ts":1634392892},{"dir":"/sys/class","file":"nvme-subsystem","relpos":8,"ts":1634392892},{"dir":"/etc/bluetooth","file":"main.conf","relpos":1,"ts":1634392892},{"dir":"/etc","file":"bluetooth","relpos":12,"ts":1634392892},{"dir":"/","file":"home","relpos":4,"ts":1634392892},{"dir":"/home","file":"cliffordc","relpos":1,"ts":1634392892},{"dir":"/","file":"sys","relpos":15,"ts":1634392892},{"dir":"/sys","file":"block","relpos":1,"ts":1634392892},{"dir":"/sys/block","file":"loop0","relpos":1,"ts":1634392892},{"dir":"/sys","file":"bus","relpos":2,"ts":1634392892},{"dir":"/sys/bus","file":"gpio","relpos":11,"ts":1634392892},{"dir":"/sys","file":"class","relpos":3,"ts":1634392892},{"dir":"/sys/class","file":"nvme-subsystem","relpos":8,"ts":1634392892},{"dir":"/etc/bluetooth","file":"main.conf","relpos":1,"ts":1634392892},{"dir":"/etc","file":"bluetooth","relpos":12,"ts":1634392892},{"dir":"/","file":"home","relpos":4,"ts":1634392892},{"dir":"/home","file":"cliffordc","relpos":1,"ts":1634392892},{"dir":"/","file":"sys","relpos":15,"ts":1634392892},{"dir":"/sys","file":"block","relpos":1,"ts":1634392892},{"dir":"/sys/block","file":"loop0","relpos":1,"ts":1634392892},{"dir":"/sys","file":"bus","relpos":2,"ts":1634392892},{"dir":"/sys/bus","file":"gpio","relpos":11,"ts":1634392892},{"dir":"/sys","file":"class","relpos":3,"ts":1634392892},{"dir":"/sys/class","file":"nvme-subsystem","relpos":13,"ts":1634392892},{"dir":"/etc/bluetooth","file":"main.conf","relpos":1,"ts":1634392892},{"dir":"/etc","file":"bluetooth","relpos":12,"ts":1634392892},{"dir":"/","file":"home","relpos":4,"ts":1634392892},{"dir":"/home","file":"cliffordc","relpos":1,"ts":1634392892},{"dir":"/","file":"sys","relpos":15,"ts":1634392892},{"dir":"/sys","file":"block","relpos":1,"ts":1634392892},{"dir":"/sys/block","file":"loop0","relpos":1,"ts":1634392892},{"dir":"/sys","file":"bus","relpos":2,"ts":1634392892},{"dir":"/sys/bus","file":"gpio","relpos":11,"ts":1634392892},{"dir":"/sys","file":"class","relpos":3,"ts":1634392892},{"dir":"/sys/class","file":"nvme-subsystem","relpos":8,"ts":1634392892},{"dir":"/etc/bluetooth","file":"main.conf","relpos":1,"ts":1634392892},{"dir":"/etc","file":"bluetooth","relpos":12,"ts":1634392892},{"dir":"/","file":"home","relpos":4,"ts":1634392892},{"dir":"/home","file":"cliffordc","relpos":1,"ts":1634392892},{"dir":"/","file":"sys","relpos":15,"ts":1634392892},{"dir":"/sys","file":"block","relpos":1,"ts":1634392892},{"dir":"/sys/block","file":"loop0","relpos":1,"ts":1634392892},{"dir":"/sys","file":"bus","relpos":2,"ts":1634392892},{"dir":"/sys/bus","file":"gpio","relpos":11,"ts":1634392892},{"dir":"/sys","file":"class","relpos":3,"ts":1634392892},{"dir":"/sys/class","file":"nvme-subsystem","relpos":8,"ts":1634392892},{"dir":"/etc/bluetooth","file":"main.conf","relpos":1,"ts":1634392892},{"dir":"/etc","file":"bluetooth","relpos":12,"ts":1634392892},{"dir":"/","file":"home","relpos":4,"ts":1634392892},{"dir":"/home","file":"cliffordc","relpos":1,"ts":1634392892},{"dir":"/","file":"sys","relpos":15,"ts":1634392892},{"dir":"/sys","file":"block","relpos":1,"ts":1634392892},{"dir":"/sys/block","file":"loop0","relpos":1,"ts":1634392892},{"dir":"/sys","file":"bus","relpos":2,"ts":1634392892},{"dir":"/sys/bus","file":"gpio","relpos":11,"ts":1634392892},{"dir":"/sys","file":"class","relpos":3,"ts":1634392892},{"dir":"/sys/class","file":"nvme-subsystem","relpos":13,"ts":1634392892},{"dir":"/etc/bluetooth","file":"main.conf","relpos":1,"ts":1634392892},{"dir":"/etc","file":"bluetooth","relpos":12,"ts":1634392892},{"dir":"/","file":"home","relpos":4,"ts":1634392892},{"dir":"/home","file":"cliffordc","relpos":1,"ts":1634392892},{"dir":"/","file":"sys","relpos":15,"ts":1634392892},{"dir":"/sys","file":"block","relpos":1,"ts":1634392892},{"dir":"/sys/block","file":"loop0","relpos":1,"ts":1634392892},{"dir":"/sys","file":"bus","relpos":2,"ts":1634392892},{"dir":"/sys/bus","file":"gpio","relpos":11,"ts":1634392892},{"dir":"/sys","file":"class","relpos":3,"ts":1634392892},{"dir":"/sys/class","file":"nvme-subsystem","relpos":8,"ts":1634392892},{"dir":"/etc/bluetooth","file":"main.conf","relpos":1,"ts":1634392892},{"dir":"/etc","file":"bluetooth","relpos":12,"ts":1634392892},{"dir":"/","file":"home","relpos":4,"ts":1634392892},{"dir":"/home","file":"cliffordc","relpos":1,"ts":1634392892},{"dir":"/","file":"sys","relpos":15,"ts":1634392892},{"dir":"/sys","file":"block","relpos":1,"ts":1634392892},{"dir":"/sys/block","file":"loop0","relpos":1,"ts":1634392892},{"dir":"/sys","file":"bus","relpos":2,"ts":1634392892},{"dir":"/sys/bus","file":"gpio","relpos":11,"ts":1634392892},{"dir":"/sys","file":"class","relpos":3,"ts":1634392892},{"dir":"/sys/class","file":"nvme-subsystem","relpos":8,"ts":1634392892}],"filters":{"invert":true,"dot":false,"manual":"","auto":""},"last-location":"/sys/class","sorting":[2],"preview":true}]}],"active-pane":0,"preview":true,"splitter":{"pos":-1,"ratio":0.5,"orientation":"v","expanded":false}}],"trash":[{"trashed":"/home/cliffordc/.local/share/vifm/Trash/000_.android","original":"/home/cliffordc/.android"},{"trashed":"/home/cliffordc/.local/share/vifm/Trash/000_alacritty","original":"/home/cliffordc/.config/alacritty"},{"trashed":"/home/cliffordc/.local/share/vifm/Trash/000_flameshot","original":"/home/cliffordc/.config/flameshot"},{"trashed":"/home/cliffordc/.local/share/vifm/Trash/000_.git","original":"/home/cliffordc/.config/nvim/.git"},{"trashed":"/home/cliffordc/.local/share/vifm/Trash/003_.git","original":"/home/cliffordc/.config/nvim/.git"},{"trashed":"/home/cliffordc/.local/share/vifm/Trash/000_coc-settings.json","original":"/home/cliffordc/.config/nvim/coc-settings.json"},{"trashed":"/home/cliffordc/.local/share/vifm/Trash/001_coc-settings.json","original":"/home/cliffordc/.config/nvim/coc-settings.json"},{"trashed":"/home/cliffordc/.local/share/vifm/Trash/000_completion.lua","original":"/home/cliffordc/.config/nvim/lua/completion.lua"},{"trashed":"/home/cliffordc/.local/share/vifm/Trash/000_everforest.lua","original":"/home/cliffordc/.config/nvim/lua/everforest.lua"},{"trashed":"/home/cliffordc/.local/share/vifm/Trash/000_format.lua","original":"/home/cliffordc/.config/nvim/lua/format.lua"},{"trashed":"/home/cliffordc/.local/share/vifm/Trash/000_git-signs.lua","original":"/home/cliffordc/.config/nvim/lua/git-signs.lua"},{"trashed":"/home/cliffordc/.local/share/vifm/Trash/000_gutter.lua","original":"/home/cliffordc/.config/nvim/lua/gutter.lua"},{"trashed":"/home/cliffordc/.local/share/vifm/Trash/001_gutter.lua","original":"/home/cliffordc/.config/nvim/lua/gutter.lua"},{"trashed":"/home/cliffordc/.local/share/vifm/Trash/000_vimscript","original":"/home/cliffordc/.config/nvim/vimscript"},{"trashed":"/home/cliffordc/.local/share/vifm/Trash/000_airline.vim","original":"/home/cliffordc/.config/nvim/vimscript/airline.vim"},{"trashed":"/home/cliffordc/.local/share/vifm/Trash/001_airline.vim","original":"/home/cliffordc/.config/nvim/vimscript/airline.vim"},{"trashed":"/home/cliffordc/.local/share/vifm/Trash/000_coc.vim","original":"/home/cliffordc/.config/nvim/vimscript/coc.vim"},{"trashed":"/home/cliffordc/.local/share/vifm/Trash/001_coc.vim","original":"/home/cliffordc/.config/nvim/vimscript/coc.vim"},{"trashed":"/home/cliffordc/.local/share/vifm/Trash/000_redshift.conf","original":"/home/cliffordc/.config/redshift.conf"},{"trashed":"/home/cliffordc/.local/share/vifm/Trash/000_config","original":"/home/cliffordc/.config/rofi/config"},{"trashed":"/home/cliffordc/.local/share/vifm/Trash/000_config.rasi","original":"/home/cliffordc/.config/rofi/config.rasi"},{"trashed":"/home/cliffordc/.local/share/vifm/Trash/000_powermenu","original":"/home/cliffordc/.config/rofi/powermenu"},{"trashed":"/home/cliffordc/.local/share/vifm/Trash/000_powermenu.sh","original":"/home/cliffordc/.config/rofi/powermenu.sh"},{"trashed":"/home/cliffordc/.local/share/vifm/Trash/000_scripts","original":"/home/cliffordc/.config/rofi/scripts"},{"trashed":"/home/cliffordc/.local/share/vifm/Trash/000_themes","original":"/home/cliffordc/.config/rofi/themes"},{"trashed":"/home/cliffordc/.local/share/vifm/Trash/000_.emacs.d","original":"/home/cliffordc/.emacs.d"},{"trashed":"/home/cliffordc/.local/share/vifm/Trash/000_.saves-13408-clifford-zenbookux425iaum425ia~","original":"/home/cliffordc/.emacs.d/auto-save-list/.saves-13408-clifford-zenbookux425iaum425ia~"},{"trashed":"/home/cliffordc/.local/share/vifm/Trash/000_.saves-3150-clifford-zenbookux425iaum425ia~","original":"/home/cliffordc/.emacs.d/auto-save-list/.saves-3150-clifford-zenbookux425iaum425ia~"},{"trashed":"/home/cliffordc/.local/share/vifm/Trash/000_.saves-4435-clifford-zenbookux425iaum425ia~","original":"/home/cliffordc/.emacs.d/auto-save-list/.saves-4435-clifford-zenbookux425iaum425ia~"},{"trashed":"/home/cliffordc/.local/share/vifm/Trash/000_userContent.css","original":"/home/cliffordc/.librewolf/w50izy8g.default-release/chrome/userContent.css"},{"trashed":"/home/cliffordc/.local/share/vifm/Trash/000_\\","original":"/home/cliffordc/.librewolf/w50izy8g.default-release/startscreen/\\"},{"trashed":"/home/cliffordc/.local/share/vifm/Trash/000_discord.svg","original":"/home/cliffordc/.librewolf/w50izy8g.default-release/startscreen/icons/discord.svg"},{"trashed":"/home/cliffordc/.local/share/vifm/Trash/000_.omnisharp","original":"/home/cliffordc/.omnisharp"},{"trashed":"/home/cliffordc/.local/share/vifm/Trash/000_.p10k.zsh","original":"/home/cliffordc/.p10k.zsh"},{"trashed":"/home/cliffordc/.local/share/vifm/Trash/001_.p10k.zsh","original":"/home/cliffordc/.p10k.zsh"},{"trashed":"/home/cliffordc/.local/share/vifm/Trash/000_.vim","original":"/home/cliffordc/.vim"},{"trashed":"/home/cliffordc/.local/share/vifm/Trash/000_Android","original":"/home/cliffordc/Android"},{"trashed":"/home/cliffordc/.local/share/vifm/Trash/000_AndroidStudioProjects","original":"/home/cliffordc/AndroidStudioProjects"},{"trashed":"/home/cliffordc/.local/share/vifm/Trash/000_Tree.pxo","original":"/home/cliffordc/Desktop/Tree.pxo"},{"trashed":"/home/cliffordc/.local/share/vifm/Trash/000_Assignment1.zip","original":"/home/cliffordc/Documents/Algorithms/Assignment1.zip"},{"trashed":"/home/cliffordc/.local/share/vifm/Trash/000_nvim","original":"/home/cliffordc/Documents/Dotfiles/nvim"},{"trashed":"/home/cliffordc/.local/share/vifm/Trash/000_.git","original":"/home/cliffordc/Documents/Dotfiles/zsh/powerlevel10k/.git"},{"trashed":"/home/cliffordc/.local/share/vifm/Trash/000_stylua","original":"/home/cliffordc/Downloads/stylua"},{"trashed":"/home/cliffordc/.local/share/vifm/Trash/000_stylua-0.10.1-linux.zip","original":"/home/cliffordc/Downloads/stylua-0.10.1-linux.zip"},{"trashed":"/home/cliffordc/.local/share/vifm/Trash/000_Screenshot from 2021-08-10 16-17-42.png","original":"/home/cliffordc/Pictures/Screenshot from 2021-08-10 16-17-42.png"},{"trashed":"/home/cliffordc/.local/share/vifm/Trash/000_index.css","original":"/home/cliffordc/Projects/Carrot/src/index.css"},{"trashed":"/home/cliffordc/.local/share/vifm/Trash/000_index.html","original":"/home/cliffordc/Projects/Carrot/src/index.html"},{"trashed":"/home/cliffordc/.local/share/vifm/Trash/002_.git","original":"/home/cliffordc/Projects/carrot/.git"},{"trashed":"/home/cliffordc/.local/share/vifm/Trash/000_.gitignore","original":"/home/cliffordc/Projects/carrot/.gitignore"},{"trashed":"/home/cliffordc/.local/share/vifm/Trash/001_README.md","original":"/home/cliffordc/Projects/carrot/README.md"},{"trashed":"/home/cliffordc/.local/share/vifm/Trash/000_favicon.ico","original":"/home/cliffordc/Projects/website/public/favicon.ico"},{"trashed":"/home/cliffordc/.local/share/vifm/Trash/000_logo192.png","original":"/home/cliffordc/Projects/website/public/logo192.png"},{"trashed":"/home/cliffordc/.local/share/vifm/Trash/000_logo512.png","original":"/home/cliffordc/Projects/website/public/logo512.png"},{"trashed":"/home/cliffordc/.local/share/vifm/Trash/000_logo.svg","original":"/home/cliffordc/Projects/website/src/logo.svg"},{"trashed":"/home/cliffordc/.local/share/vifm/Trash/000_cht.sh","original":"/home/cliffordc/cht.sh"},{"trashed":"/home/cliffordc/.local/share/vifm/Trash/000_dick","original":"/home/cliffordc/dick"},{"trashed":"/home/cliffordc/.local/share/vifm/Trash/000_package-lock.json","original":"/home/cliffordc/package-lock.json"},{"trashed":"/home/cliffordc/.local/share/vifm/Trash/000_package.json","original":"/home/cliffordc/package.json"},{"trashed":"/home/cliffordc/.local/share/vifm/Trash/000_powerlevel10k","original":"/home/cliffordc/powerlevel10k"},{"trashed":"/home/cliffordc/.local/share/vifm/Trash/001_.git","original":"/home/cliffordc/tmux/nord-tmux/.git"},{"trashed":"/home/cliffordc/.local/share/vifm/Trash/000_CHANGELOG.md","original":"/home/cliffordc/tmux/nord-tmux/CHANGELOG.md"},{"trashed":"/home/cliffordc/.local/share/vifm/Trash/000_LICENSE.md","original":"/home/cliffordc/tmux/nord-tmux/LICENSE.md"},{"trashed":"/home/cliffordc/.local/share/vifm/Trash/000_README.md","original":"/home/cliffordc/tmux/nord-tmux/README.md"},{"trashed":"/home/cliffordc/.local/share/vifm/Trash/000_yes.svelte","original":"/home/cliffordc/yes.svelte"}],"marks":{"H":{"dir":"/home/cliffordc/","file":"..","ts":1628524619},"b":{"dir":"/home/cliffordc/bin/","file":"..","ts":1628524619},"d":{"dir":"/home/cliffordc/.config","file":"polybar","ts":1629512588},"h":{"dir":"/home/cliffordc/","file":"..","ts":1628524619},"n":{"dir":"/home/cliffordc/.config/nvim","file":"lua","ts":1628670278},"p":{"dir":"/home/cliffordc/Projects","file":"portfolio","ts":1630486787},"w":{"dir":"/home/cliffordc/Projects/carrotOnAStick/src","file":"App.svelte","ts":1628967435},"z":{"dir":"/home/cliffordc/.config/vifm","file":"..","ts":1628524619}},"bmarks":{},"cmd-hist":[{"text":"mkdir chrome","ts":1628528031},{"text":"!nvim userChrome.css","ts":1628528118},{"text":"!nvim alacritty.","ts":1628582145},{"text":"mkdir lua","ts":1628585525},{"text":"mkdir vimscript","ts":1628585525},{"text":"!nvim settings.lua","ts":1628585525},{"text":"!nvim keymaps.lua","ts":1628585525},{"text":"!nvim init.vim","ts":1628585525},{"text":"!nvim plugins.lua","ts":1628585525},{"text":"!nvim coc.vim","ts":1628586999},{"text":"!nvim airline.vim","ts":1628586999},{"text":"ivfm","ts":1628589508},{"text":"!nvim vifmimg","ts":1628589508},{"text":"!nvim vifmrun","ts":1628589508},{"text":"!nvim compile.vim","ts":1628594251},{"text":"!nvim","ts":1628595430},{"text":"mkdir rofi","ts":1628595430},{"text":"!nvim colors.ini","ts":1628595435},{"text":"!nvim config.ini","ts":1628595435},{"text":"!nvim modules.ini","ts":1628595435},{"text":"!nvim launch.sh","ts":1628595435},{"text":"!nvim slate","ts":1628596235},{"text":"!nvim picom.conf","ts":1628596733},{"text":"!nvim telescope-config.lua","ts":1628603965},{"text":"w","ts":1628605361},{"text":"mkdir ","ts":1628655988},{"text":"mkdir Dotfiles","ts":1628655988},{"text":"mkdir librewolfcss","ts":1628655988},{"text":"mkdir nvim","ts":1628655988},{"text":"mkdir vifm","ts":1628655988},{"text":"!nvim ifm","ts":1628655988},{"text":"mkdir bspwm","ts":1628655988},{"text":"mkdir zsh","ts":1628655988},{"text":"mkdir polybar","ts":1628655988},{"text":"mkdir tmux","ts":1628743692},{"text":"!nvim Assignment1.c","ts":1628828620},{"text":"!nvim Assignment.txt","ts":1628828620},{"text":"zip Assignment1/","ts":1628828620},{"text":"!nvim yes.svelte","ts":1628938240},{"text":"!nvim git-signs.lua","ts":1628953739},{"text":"!nvim st at","ts":1628959407},{"text":"!nvim statusline.lua","ts":1628959407},{"text":"mkdir clifford","ts":1629022450},{"text":"mkdir telescope","ts":1629022450},{"text":"v init.lua","ts":1629022450},{"text":"!nvim init.lua","ts":1629022450},{"text":"!nvim Nord.css","ts":1629027189},{"text":"!nvim App.svelte","ts":1629101665},{"text":"mkdir components","ts":1629105635},{"text":"!nvim timer.svelte","ts":1629105635},{"text":"!nvim reports.svelte","ts":1629105635},{"text":"!nvim settings.svelte","ts":1629105635},{"text":"mkdir alacritty","ts":1629351225},{"text":"wq","ts":1629351225},{"text":"!nvim alacritty.yml","ts":1629351538},{"text":"!nvim if","ts":1629680721},{"text":"!nvim startscreen.html","ts":1629790524},{"text":"mkdir Applications","ts":1629949646},{"text":"!nvim completion.lua","ts":1629953092},{"text":"!nvim autopairs.lua","ts":1629954191},{"text":"!nvim formatter.lua","ts":1629959874},{"text":"!nvim emmet.lua","ts":1629985018},{"text":"mkdir fonts","ts":1630035109},{"text":"!nvim protonvpn.sh","ts":1630119448},{"text":"!nvim gitsigns","ts":1630132125},{"text":"!nvim gitsigns.lua","ts":1630132125},{"text":"!nvim bufferline.lua","ts":1630381444},{"text":"!nvim icons.lua","ts":1630383666},{"text":"mkdir scripts","ts":1630561468},{"text":"!nvim rofi-power","ts":1630561468},{"text":"mkdir powermenu","ts":1630591079},{"text":"!nvim rofipowermenu","ts":1630591079},{"text":"!nvim powermenu.sh","ts":1630591079},{"text":"!nvim gutter.lua","ts":1630773563},{"text":"!nvim i","ts":1630817199},{"text":"vifm man","ts":1630817199},{"text":"man","ts":1630817199},{"text":"plug","ts":1630818577},{"text":"mkdir themes","ts":1630823719},{"text":"!nvim photon.rasi","ts":1630823719},{"text":"!nvim slate.rasi","ts":1630824036},{"text":"!nvim onedark.rasi","ts":1630824091},{"text":"!nvim dracula.rasi","ts":1630824794},{"text":"!nvim ","ts":1630824897},{"text":"!nvim squared.rasi","ts":1630830511},{"text":"!nvim prettier.lua","ts":1630861690},{"text":"mkdir lspconfig","ts":1630908507},{"text":"mkdir sumneko_lua","ts":1630908507},{"text":"DirEnter","ts":1630912600},{"text":"colorscheme","ts":1630912600},{"text":"filextype","ts":1630912600},{"text":"colorscheme Default","ts":1630912600},{"text":"!nvim userContent.css","ts":1631510805},{"text":"mkdir tint2","ts":1634197629},{"text":"!nvim powermenu.rasi","ts":1634197629},{"text":"vifm","ts":1635767202},{"text":"dot","ts":1635767202},{"text":"vif","ts":1635767202},{"text":"help","ts":1635767202},{"text":"q","ts":1638513913}],"search-hist":[{"text":"alacri","ts":1630745106},{"text":"se","ts":1630773972},{"text":"stat","ts":1630776269},{"text":"sxhd","ts":1630832468},{"text":"pol","ts":1630834238},{"text":"form","ts":1630859610},{"text":"loca","ts":1630861759},{"text":"seting","ts":1630906798},{"text":".","ts":1630908507},{"text":".cache","ts":1630908507},{"text":"pIcutre","ts":1630910663},{"text":".cofnig","ts":1630910973},{"text":"Pict","ts":1630911014},{"text":"eva","ts":1630911875},{"text":"Al","ts":1630912008},{"text":"Dopc","ts":1630912642},{"text":"vifm","ts":1630913135},{"text":"vs","ts":1630987067},{"text":"ranger","ts":1630987549},{"text":"cmus","ts":1630987788},{"text":"statu","ts":1630990288},{"text":"prettier","ts":1631159300},{"text":"plugi","ts":1631159300},{"text":"settin","ts":1631182550},{"text":"Proje","ts":1631247203},{"text":"line","ts":1631382000},{"text":"setting","ts":1631387600},{"text":"icons","ts":1631417567},{"text":"libre","ts":1631418055},{"text":"alacr","ts":1631422384},{"text":"zs","ts":1631431659},{"text":"p10k","ts":1631431659},{"text":"sxh","ts":1631590786},{"text":"xinit","ts":1631591467},{"text":"Notes","ts":1631591508},{"text":"sx","ts":1631611324},{"text":"Pro","ts":1631697430},{"text":"gu","ts":1631962022},{"text":"Docu","ts":1631962071},{"text":"sxkd","ts":1631964102},{"text":".zshrc","ts":1632110404},{"text":"a.out","ts":1632227253},{"text":"yes.c","ts":1632227253},{"text":"togg","ts":1632227699},{"text":"plugin","ts":1632243029},{"text":"ala","ts":1632243029},{"text":"zshrc","ts":1632295182},{"text":"typescrip","ts":1632413213},{"text":"zsh","ts":1632724935},{"text":"Doc","ts":1632745821},{"text":"polybar","ts":1632831182},{"text":"bin","ts":1632915442},{"text":"csharp","ts":1632916198},{"text":"sumneko","ts":1632916198},{"text":"lua","ts":1632916198},{"text":"Linux","ts":1632916198},{"text":".l","ts":1632916198},{"text":"lspconfig","ts":1632918066},{"text":"cache","ts":1632918066},{"text":"lsp","ts":1632918066},{"text":"vim","ts":1632918066},{"text":"local","ts":1632918066},{"text":"read.c","ts":1633675636},{"text":"Docume","ts":1633675643},{"text":"Documents","ts":1633675643},{"text":"tels","ts":1633676134},{"text":"rofi","ts":1634197629},{"text":"tint2","ts":1634197811},{"text":"blut","ts":1634392771},{"text":"blueJJJ","ts":1634392771},{"text":"lib","ts":1634392892},{"text":"blue","ts":1634392892},{"text":"usr","ts":1634405215},{"text":"grub","ts":1634405215},{"text":"poly","ts":1634923289},{"text":"completion","ts":1635601218},{"text":"e","ts":1635767283},{"text":"emacs","ts":1635767283},{"text":".librewolf","ts":1635768020},{"text":"chrome","ts":1635768020},{"text":"start","ts":1635768020},{"text":"Downloads","ts":1635768155},{"text":"Pictures","ts":1635768155},{"text":"Down","ts":1635768155},{"text":"downloads","ts":1635768201},{"text":".libre","ts":1635768201},{"text":".config","ts":1635770246},{"text":"bspw","ts":1635770246},{"text":"pictures","ts":1635914690},{"text":"pictu","ts":1635914821},{"text":"down","ts":1635914821},{"text":"pic","ts":1635914821},{"text":"sxhkd","ts":1638513913},{"text":"bspwm","ts":1638514895},{"text":"gutter","ts":1638709760},{"text":"alac","ts":1638709760},{"text":"nvim","ts":1638766095},{"text":"plug","ts":1638766095},{"text":"ke","ts":1638766095},{"text":"comple","ts":1638766740}],"prompt-hist":[{"text":"sakura","ts":1628585565},{"text":"Sakura","ts":1628585565},{"text":"Everforest","ts":1628588706},{"text":"nf","ts":1628604165},{"text":"config","ts":1628605361},{"text":"main.js","ts":1629101665},{"text":"svelte","ts":1629101665},{"text":"App.svelte","ts":1629104175},{"text":"app","ts":1629104175},{"text":"config.ini","ts":1629516351},{"text":"compile","ts":1629958937},{"text":"compile.lua","ts":1629958937},{"text":"init.lua","ts":1629959113},{"text":"settings.lua","ts":1629959113},{"text":"basicsettings","ts":1629959113},{"text":"basicsettings.lua","ts":1629959113},{"text":"settings","ts":1629959113},{"text":"formatter.lua","ts":1629959874},{"text":"format","ts":1629959874},{"text":"gutter","ts":1629967549},{"text":"buffer.lua","ts":1630381444},{"text":"App.jsx","ts":1630487471},{"text":"app.svelteSDFJKLASDJFKLJASKLDFJKLSFJq","ts":1630645683},{"text":"app.svelte","ts":1631247203},{"text":"icons8-discord-bubble.svg","ts":1635768201},{"text":"discord","ts":1635768201}],"regs":{},"dir-stack":[],"use-term-multiplexer":false}